aws_agentcore_mcp_server/__init__.py
aws_agentcore_mcp_server/__main__.py
aws_agentcore_mcp_server/server.py
aws_agentcore_mcp_server/content/code_interpreter.md
aws_agentcore_mcp_server/content/gateway.md
aws_agentcore_mcp_server/content/identity.md
aws_agentcore_mcp_server/content/memory.md
aws_agentcore_mcp_server/content/observability.md
aws_agentcore_mcp_server/content/quickstart.md
aws_agentcore_mcp_server/content/tools.md
aws_agentcore_mcp_server-0.1.4.dist-info/METADATA
aws_agentcore_mcp_server-0.1.4.dist-info/WHEEL
aws_agentcore_mcp_server-0.1.4.dist-info/entry_points.txt
aws_agentcore_mcp_server-0.1.4.dist-info/licenses/LICENSE
aws_agentcore_mcp_server-0.1.4.dist-info/RECORD
